my_investimento/__init__.py
my_investimento/core.py
my_investimento_package-1.0.0.dist-info/METADATA
my_investimento_package-1.0.0.dist-info/WHEEL
my_investimento_package-1.0.0.dist-info/top_level.txt
my_investimento_package-1.0.0.dist-info/RECORD
