Metadata-Version: 2.1
Name: my-investimento-package
Version: 1.0.0
Summary: Descricao da sua lib my_investimento
Home-page: https://github.com/tadrianonet/my_investimento
Author: Marcelo N Morais
Author-email: marcnobremorais@gmail.com
License: MIT
Platform: UNKNOWN
